cnslab/__init__.py
cnslab-0.0.1.dist-info/METADATA
cnslab-0.0.1.dist-info/WHEEL
cnslab-0.0.1.dist-info/top_level.txt
cnslab-0.0.1.dist-info/RECORD
