Metadata-Version: 2.1
Name: cnslab
Version: 0.0.1
Summary: Help! CNS lab
Home-page: UNKNOWN
Author: Ather Py 
Author-email: <staging61@gmail.com>
License: UNKNOWN
Keywords: python
Platform: UNKNOWN
Classifier: Development Status :: 1 - Planning
Classifier: Intended Audience :: Developers
Classifier: Programming Language :: Python :: 3
Classifier: Operating System :: Unix
Classifier: Operating System :: MacOS :: MacOS X
Classifier: Operating System :: Microsoft :: Windows
